benchmarks/README.md
benchmarks/__init__.py
benchmarks/regression/README.md
benchmarks/regression/asv.conf.json
benchmarks/regression/benchmarks/__init__.py
benchmarks/regression/benchmarks/acoustic.py
benchmarks/regression/benchmarks/arguments.py
benchmarks/regression/benchmarks/codegen.py
benchmarks/regression/benchmarks/simple_operators.py
benchmarks/user/README.md
benchmarks/user/__init__.py
benchmarks/user/benchmark.py
benchmarks/user/advisor/README.md
benchmarks/user/advisor/__init__.py
benchmarks/user/advisor/advisor_logging.py
benchmarks/user/advisor/roofline.py
benchmarks/user/advisor/run_advisor.py
devito/__init__.py
devito/deprecations.py
devito/exceptions.py
devito/logger.py
devito/parameters.py
devito/warnings.py
devito/arch/__init__.py
devito/arch/archinfo.py
devito/arch/compiler.py
devito/builtins/__init__.py
devito/builtins/arithmetic.py
devito/builtins/initializers.py
devito/builtins/utils.py
devito/checkpointing/__init__.py
devito/checkpointing/checkpoint.py
devito/core/__init__.py
devito/core/arm.py
devito/core/autotuning.py
devito/core/cpu.py
devito/core/gpu.py
devito/core/intel.py
devito/core/operator.py
devito/core/power.py
devito/data/__init__.py
devito/data/allocators.py
devito/data/data.py
devito/data/decomposition.py
devito/data/meta.py
devito/data/utils.py
devito/finite_differences/__init__.py
devito/finite_differences/coefficients.py
devito/finite_differences/derivative.py
devito/finite_differences/differentiable.py
devito/finite_differences/elementary.py
devito/finite_differences/finite_difference.py
devito/finite_differences/operators.py
devito/finite_differences/rsfd.py
devito/finite_differences/tools.py
devito/ir/__init__.py
devito/ir/cgen/__init__.py
devito/ir/cgen/printer.py
devito/ir/clusters/__init__.py
devito/ir/clusters/algorithms.py
devito/ir/clusters/analysis.py
devito/ir/clusters/cluster.py
devito/ir/clusters/visitors.py
devito/ir/equations/__init__.py
devito/ir/equations/algorithms.py
devito/ir/equations/equation.py
devito-4.8.20.dist-info/licenses/LICENSE.md
devito-4.8.20.dist-info/METADATA
devito-4.8.20.dist-info/WHEEL
devito-4.8.20.dist-info/top_level.txt
devito-4.8.20.dist-info/RECORD
