Metadata-Version: 2.4
Name: devito
Version: 4.8.20
Summary: Finite Difference DSL for symbolic computation.
Author-email: Imperial College London <g.gorman@imperial.ac.uk>, Fabio Luporini <fabio@devitocodes.com>, Mathias Louboutin <mathias@devitocodes.com>
Maintainer-email: Fabio Luporini <fabio@devitocodes.com>, Mathias Louboutin <mathias@devitocodes.com>, Gerard Gorman <gerard@devitocodes.com>
License: The MIT License (MIT)
Project-URL: Documentation, https://www.devitoproject.org/devito/index.html
Project-URL: Repository, https://github.com/devitocodes/devito
Project-URL: Issues, https://github.com/devitocodes/devito/issues
Keywords: finite-difference,DSL,symbolic,jit,devito
Classifier: Development Status :: 5 - Production/Stable
Classifier: Intended Audience :: Developers
Classifier: Intended Audience :: Science/Research
Classifier: Intended Audience :: Education
Classifier: License :: OSI Approved :: MIT License
Classifier: Operating System :: MacOS
Classifier: Operating System :: POSIX :: Linux
Classifier: Operating System :: Unix
Classifier: Programming Language :: Python
Classifier: Programming Language :: Python :: 3
Classifier: Programming Language :: Python :: 3.10
Classifier: Programming Language :: Python :: 3.11
Classifier: Programming Language :: Python :: 3.12
Classifier: Programming Language :: Python :: 3 :: Only
Classifier: Topic :: Scientific/Engineering
Classifier: Topic :: Scientific/Engineering :: Mathematics
Classifier: Topic :: Scientific/Engineering :: Physics
Classifier: Topic :: Software Development :: Code Generators
Classifier: Topic :: Software Development :: Compilers
Requires-Python: <3.14,>=3.10
License-File: LICENSE.md
Requires-Dist: pip>=9.0.1
Requires-Dist: numpy<=2.3.1,>=2
Requires-Dist: sympy<1.15,>=1.12.1
Requires-Dist: psutil<8.0,>=5.1.0
Requires-Dist: py-cpuinfo<10
Requires-Dist: cgen<2026,>=2020.1
Requires-Dist: codepy<2025,>=2019.1
Requires-Dist: multidict<6.3
Requires-Dist: anytree<=2.13.0,>=2.4.3
Requires-Dist: cloudpickle<3.1.2
Requires-Dist: packaging<25.1
Provides-Extra: mpi
Requires-Dist: mpi4py<4.1.1; extra == "mpi"
Requires-Dist: ipyparallel<9.1; extra == "mpi"
Provides-Extra: nvidia
Requires-Dist: cupy-cuda12x<13.6.1; extra == "nvidia"
Requires-Dist: dask-cuda<25.8.1; extra == "nvidia"
Requires-Dist: jupyterlab<4.4.2,>=3; extra == "nvidia"
Requires-Dist: jupyterlab-nvdashboard<0.13.1; extra == "nvidia"
Requires-Dist: dask_labextension<7.0.1; extra == "nvidia"
Requires-Dist: fsspec<2025.7.1; extra == "nvidia"
Provides-Extra: tests
Requires-Dist: pytest<8.5,>=7.2; extra == "tests"
Requires-Dist: pytest-runner<6.0.2; extra == "tests"
Requires-Dist: pytest-cov<6.2.2; extra == "tests"
Requires-Dist: flake8-pyproject<1.2.4,>=1.2.3; extra == "tests"
Requires-Dist: nbval<0.11.1; extra == "tests"
Requires-Dist: scipy<1.15.4; extra == "tests"
Requires-Dist: pooch<1.8.3; extra == "tests"
Requires-Dist: click<9.0; extra == "tests"
Provides-Extra: extras
Requires-Dist: matplotlib<3.10.7; extra == "extras"
Requires-Dist: pillow<11.3.1,>11; extra == "extras"
Requires-Dist: pyrevolve==2.2.6; extra == "extras"
Requires-Dist: scipy<1.15.4; extra == "extras"
Requires-Dist: distributed<2025.7.1; extra == "extras"
Requires-Dist: click<9.0; extra == "extras"
Dynamic: license-file
